nutai/__init__.py
nutai/__main__.py
nutai/api.py
nutai/doc2vec.py
nutai/helpers.py
nutai/minhash.py
nutai/nutai.yaml
nutai-0.4.0.dist-info/LICENSE
nutai-0.4.0.dist-info/METADATA
nutai-0.4.0.dist-info/WHEEL
nutai-0.4.0.dist-info/top_level.txt
nutai-0.4.0.dist-info/RECORD
