Metadata-Version: 2.1
Name: nutai
Version: 0.4.0
Summary: UNKNOWN
Home-page: https://github.com/mattf/nutai
Author: Matthew Farrellee
Author-email: matt@cs.wisc.edu
License: UNKNOWN
Platform: UNKNOWN
Classifier: Programming Language :: Python :: 3
Classifier: License :: OSI Approved :: GNU Affero General Public License v3
Classifier: Operating System :: OS Independent
Requires-Python: >=3.6
Requires-Dist: connexion[swagger-ui]
Requires-Dist: gensim
Requires-Dist: msgpack
Requires-Dist: msgpack-numpy
Requires-Dist: numpy
Requires-Dist: sklearn
Requires-Dist: tqdm
Requires-Dist: redis
Requires-Dist: minhash
Requires-Dist: mfoops
